covid_alarm_clock/__init__.py
covid_alarm_clock/fetch_data.py
covid_alarm_clock/main.py
tests/__init__.py
tests/test_fetch_data.py
LukeCollishaw-1.0.0.dist-info/LICENSE.md
LukeCollishaw-1.0.0.dist-info/METADATA
LukeCollishaw-1.0.0.dist-info/WHEEL
LukeCollishaw-1.0.0.dist-info/top_level.txt
LukeCollishaw-1.0.0.dist-info/RECORD
