Metadata-Version: 2.1
Name: LukeCollishaw
Version: 1.0.0
Summary: COVID Alarm Clock
Home-page: https://github.com/lc796/covid-alarm-clock
Author: Luke Collishaw-Schepman
Author-email: lc796@exeter.ac.uk
License: UNKNOWN
Platform: UNKNOWN
Classifier: Programming Language :: Python :: 3
Classifier: Operating System :: OS Independent
Requires-Python: >=3.6
